project_forge/__init__.py
project_forge/__main__.py
project_forge/caching.py
project_forge/cli.py
project_forge/git_commands.py
project_forge/path_matching.py
project_forge/settings.py
project_forge/utils.py
project_forge/commands/__init__.py
project_forge/commands/build.py
project_forge/commands/export_schemas.py
project_forge/context_builder/__init__.py
project_forge/context_builder/context.py
project_forge/context_builder/data_merge.py
project_forge/context_builder/overlays.py
project_forge/context_builder/questions.py
project_forge/context_builder/tasks.py
project_forge/core/__init__.py
project_forge/core/exceptions.py
project_forge/core/io.py
project_forge/core/types.py
project_forge/core/urls.py
project_forge/core/validators.py
project_forge/models/__init__.py
project_forge/models/composition.py
project_forge/models/location.py
project_forge/models/overlay.py
project_forge/models/pattern.py
project_forge/models/task.py
project_forge/rendering/__init__.py
project_forge/rendering/environment.py
project_forge/rendering/expressions.py
project_forge/rendering/render.py
project_forge/rendering/templates.py
project_forge/testing/__init__.py
project_forge/testing/plugin.py
project_forge/ui/__init__.py
project_forge/ui/defaults.py
project_forge/ui/terminal.py
project_forge-0.6.0.dist-info/METADATA
project_forge-0.6.0.dist-info/WHEEL
project_forge-0.6.0.dist-info/entry_points.txt
project_forge-0.6.0.dist-info/licenses/LICENSE
project_forge-0.6.0.dist-info/RECORD
