Metadata-Version: 2.4
Name: project_forge
Version: 0.6.0
Summary: a tool that combines one or more templates and the user's answers to questions to generate a code project
Project-URL: Homepage, https://github.com/callowayproject/project-forge
Project-URL: Documentation, https://callowayproject.github.io/project_forge
Project-URL: Repository, https://github.com/callowayproject/project-forge
Project-URL: Changelog, https://github.com/callowayproject/project-forge/CHANGELOG.md
Author-email: Calloway Project <coreyoordt@gmail.com>
License: BSD License
License-File: LICENSE
Keywords: project_forge
Classifier: Development Status :: 3 - Alpha
Classifier: Framework :: Pytest
Classifier: Intended Audience :: Developers
Classifier: Natural Language :: English
Classifier: Programming Language :: Python :: 3.12
Requires-Python: >=3.12
Requires-Dist: click>=8.1.7
Requires-Dist: environs>=9.3.5
Requires-Dist: gitpython>=3.1.43
Requires-Dist: immutabledict>=4.2.0
Requires-Dist: jinja2>=3.1.0
Requires-Dist: platformdirs>=4.2.2
Requires-Dist: pydantic-settings>=2.4.0
Requires-Dist: pydantic>=2.8.2
Requires-Dist: pyyaml>=6.0.2
Requires-Dist: questionary>=2.0.1
Requires-Dist: rich-click>=1.8.3
Requires-Dist: tomlkit>=0.13.2
